camera/__init__.py
camera/main.py
rtspbuffercam-0.1.1.dist-info/METADATA
rtspbuffercam-0.1.1.dist-info/WHEEL
rtspbuffercam-0.1.1.dist-info/top_level.txt
rtspbuffercam-0.1.1.dist-info/RECORD
