Metadata-Version: 2.1
Name: rtspbuffercam
Version: 0.1.1
Summary: RTSP camera grabber with buffer exhaustion
Home-page: https://github.com/lewis-morris/rtspbuffercam
Author: Lewis Morris
Author-email: lewis.morris@gmail.com
License: MIT
Platform: UNKNOWN
